azure/mgmt/costmanagement/__init__.py
azure/mgmt/costmanagement/_configuration.py
azure/mgmt/costmanagement/_cost_management_client.py
azure/mgmt/costmanagement/_patch.py
azure/mgmt/costmanagement/_serialization.py
azure/mgmt/costmanagement/_vendor.py
azure/mgmt/costmanagement/_version.py
azure/mgmt/costmanagement/py.typed
azure/mgmt/costmanagement/aio/__init__.py
azure/mgmt/costmanagement/aio/_configuration.py
azure/mgmt/costmanagement/aio/_cost_management_client.py
azure/mgmt/costmanagement/aio/_patch.py
azure/mgmt/costmanagement/aio/operations/__init__.py
azure/mgmt/costmanagement/aio/operations/_alerts_operations.py
azure/mgmt/costmanagement/aio/operations/_benefit_recommendations_operations.py
azure/mgmt/costmanagement/aio/operations/_benefit_utilization_summaries_operations.py
azure/mgmt/costmanagement/aio/operations/_dimensions_operations.py
azure/mgmt/costmanagement/aio/operations/_exports_operations.py
azure/mgmt/costmanagement/aio/operations/_forecast_operations.py
azure/mgmt/costmanagement/aio/operations/_generate_cost_details_report_operations.py
azure/mgmt/costmanagement/aio/operations/_generate_detailed_cost_report_operation_results_operations.py
azure/mgmt/costmanagement/aio/operations/_generate_detailed_cost_report_operation_status_operations.py
azure/mgmt/costmanagement/aio/operations/_generate_detailed_cost_report_operations.py
azure/mgmt/costmanagement/aio/operations/_generate_reservation_details_report_operations.py
azure/mgmt/costmanagement/aio/operations/_operations.py
azure/mgmt/costmanagement/aio/operations/_patch.py
azure/mgmt/costmanagement/aio/operations/_price_sheet_operations.py
azure/mgmt/costmanagement/aio/operations/_query_operations.py
azure/mgmt/costmanagement/aio/operations/_scheduled_actions_operations.py
azure/mgmt/costmanagement/aio/operations/_views_operations.py
azure/mgmt/costmanagement/models/__init__.py
azure/mgmt/costmanagement/models/_cost_management_client_enums.py
azure/mgmt/costmanagement/models/_models_py3.py
azure_mgmt_costmanagement-4.0.1.dist-info/LICENSE
azure_mgmt_costmanagement-4.0.1.dist-info/METADATA
azure_mgmt_costmanagement-4.0.1.dist-info/WHEEL
azure_mgmt_costmanagement-4.0.1.dist-info/top_level.txt
azure_mgmt_costmanagement-4.0.1.dist-info/RECORD
